{
  "panel": {
    "titulo": "Panel de Actualización de Contenido - Colegio Militar General Santander",
    "campos": [
      {
        "nombre": "Fechas Importantes",
        "tipo": "lista",
        "descripcion": "Lista de fechas clave para inscripciones, matrículas, entrevistas y eventos institucionales.",
        "campos": [
          {
            "nombre": "Inicio de Inscripciones",
            "tipo": "fecha",
            "valor": ""
          },
          {
            "nombre": "Cierre de Inscripciones",
            "tipo": "fecha",
            "valor": ""
          },
          {
            "nombre": "Fechas de Entrevistas",
            "tipo": "rango_fecha",
            "valor": ""
          },
          {
            "nombre": "Inicio de Matrícula",
            "tipo": "fecha",
            "valor": ""
          },
          {
            "nombre": "Cierre de Matrícula",
            "tipo": "fecha",
            "valor": ""
          },
          {
            "nombre": "Inicio de Clases",
            "tipo": "fecha",
            "valor": ""
          }
        ]
      },
      {
        "nombre": "Horarios de Atención",
        "tipo": "texto_largo",
        "descripcion": "Horarios en los que la secretaría académica atiende para inscripciones y matrículas.",
        "valor": ""
      },
      {
        "nombre": "Requisitos de Inscripción",
        "tipo": "lista",
        "descripcion": "Documentos y pasos necesarios para la inscripción de aspirantes.",
        "campos": [
          {
            "nombre": "Compra de formulario de inscripción",
            "link":"www.test.com/formato",
            "tipo": "booleano",
            "valor": false
          },
          {
            "nombre": "Descargar y diligenciar formato de referencia",
            "link":"www.test.com/formato referencia",
            "tipo": "booleano",
            "valor": false
          },
          {
            "nombre": "Entrega de documentos adicionales",
            "link":"www.test.com/formato referencia",
            "tipo": "booleano",
            "valor": false
          }
        ]
      },
      {
        "nombre": "Grados Ofertados",
        "tipo": "lista",
        "descripcion": "Niveles y grados disponibles para inscripción.",
        "campos": [
          {
            "nombre": "Preescolar",
            "valor": "Pre-jardín, Jardín, Transición"
          },
          {
            "nombre": "Primaria",
            "valor": "1° - 5°"
          },
          {
            "nombre": "Secundaria",
            "valor": "6° - 9°"
          },
          {
            "nombre": "Media",
            "valor": "10° - 11°"
          }
        ]
      },
      {
        "nombre": "Requisitos Específicos Grado 9° (Parte Militar)",
        "tipo": "lista",
        "descripcion": "Documentos y exámenes requeridos para aspirantes a grado 9°.",
        "campos": [
          {
            "nombre": "Registros civiles originales",
            "valor": "2"
          },
          {
            "nombre": "Fotos 2.5x4.5 a color",
            "valor": "4"
          },
          {
            "nombre": "Fotocopias documento de identidad",
            "valor": "2"
          },
          {
            "nombre": "Formulario inscripción militar y formato de compromiso",
            "valor": ""
          },
          {
            "nombre": "Fotocopia informe final de logros académicos de octavo",
            "valor": ""
          },
          {
            "nombre": "Exámenes médicos",
            "valor": "Oftalmología, Otorrino, Audiometría, Radiografía pulmonar, Factor RH"
          }
        ]
      },
      {
        "nombre": "Enlaces de Interés",
        "tipo": "lista",
        "descripcion": "Enlaces útiles para descargar formatos o acceder a información relevante.",
        "campos": [
          {
            "nombre": "Formato de referencia colegio de procedencia",
            "url": "https://www.colmilgeneralsantander.edu.co/documents/001-formato_referencia.pdf"
          },
          {
            "nombre": "Sintoniza la emisora",
            "url": "https://streaminghd.co/user/radiocolmil"
          },
          {
            "nombre": "Descarga la APP de la emisora",
            "url": "https://play.google.com/store/apps/details?id=com.asiserver.radiocolmil&hl=es_CO&gl=US"
          }
        ]
      }
    ],
    "notas": "Este panel permite actualizar y mostrar la información clave para aspirantes y familias, priorizando fechas de inscripción, matrícula, horarios y requisitos. Se recomienda mantener actualizados los campos de fechas y enlaces para asegurar la correcta orientación a la comunidad educativa."
  }
}